upliftml/__init__.py
upliftml/datasets.py
upliftml/evaluation.py
upliftml/models/__init__.py
upliftml/models/h2o.py
upliftml/models/pyspark.py
upliftml/py.typed
upliftml-0.0.2.dist-info/LICENSE
upliftml-0.0.2.dist-info/WHEEL
upliftml-0.0.2.dist-info/METADATA
upliftml-0.0.2.dist-info/RECORD
