Metadata-Version: 2.1
Name: upliftml
Version: 0.0.2
Summary: A Python package for uplift modeling with PySpark and H2O
Home-page: https://github.com/bookingcom/upliftml
Author: Javier Albert
Author-email: javier.albert@booking.com
Requires-Python: >=3.7.1,<4.0.0
Classifier: Operating System :: OS Independent
Classifier: Programming Language :: Python
Classifier: Programming Language :: Python :: 3
Classifier: Programming Language :: Python :: 3.10
Classifier: Programming Language :: Python :: 3.7
Classifier: Programming Language :: Python :: 3.8
Classifier: Programming Language :: Python :: 3.9
Classifier: Topic :: Scientific/Engineering
Provides-Extra: docs
Requires-Dist: matplotlib (>=3.4.0,<4.0.0)
Requires-Dist: numpy (>=1.20.1,<2.0.0)
Requires-Dist: pandas (==1.3.5)
Requires-Dist: pydantic (>=1.8,<2.0)
Requires-Dist: scikit-learn (>=0.24,<0.25)
Requires-Dist: seaborn (>=0.11.1,<0.12.0)
Project-URL: Documentation, https://upliftml.readthedocs.io/en/latest/
Project-URL: Repository, https://github.com/bookingcom/upliftml
